ml/__init__.py
ml/api.py
ml/py.typed
ml/requirements.txt
ml/core/__init__.py
ml/core/common_types.py
ml/core/config.py
ml/core/env.py
ml/core/registry.py
ml/core/state.py
ml/launchers/__init__.py
ml/launchers/base.py
ml/launchers/ec2.py
ml/launchers/mp.py
ml/launchers/slurm.py
ml/launchers/torchrun.py
ml/loggers/__init__.py
ml/loggers/base.py
ml/loggers/meter.py
ml/loggers/multi.py
ml/loggers/stdout.py
ml/loggers/tensorboard.py
ml/loggers/wandb.py
ml/lr_schedulers/__init__.py
ml/lr_schedulers/base.py
ml/lr_schedulers/constant.py
ml/lr_schedulers/cosine.py
ml/lr_schedulers/cosine_decay.py
ml/lr_schedulers/gan.py
ml/lr_schedulers/linear.py
ml/lr_schedulers/linear_no_decay.py
ml/lr_schedulers/scripts/__init__.py
ml/lr_schedulers/scripts/plot.py
ml/models/__init__.py
ml/models/activations.py
ml/models/base.py
ml/models/embeddings.py
ml/models/gan.py
ml/models/init.py
ml/models/kmeans.py
ml/models/lora.py
ml/models/modules.py
ml/models/norms.py
ml/models/parallel.py
ml/models/architectures/__init__.py
ml/models/architectures/attention.py
ml/models/architectures/bifpn.py
ml/models/architectures/rwkv.py
ml/models/architectures/unet.py
ml/models/quantization/__init__.py
ml/models/quantization/fsq.py
ml/models/quantization/lfq.py
ml/models/quantization/vq.py
ml/optimizers/__init__.py
ml/optimizers/adam.py
ml/optimizers/adan.py
ml/optimizers/base.py
ml/optimizers/common.py
ml/optimizers/gan.py
ml/optimizers/lion.py
ml/optimizers/sgd.py
ml/optimizers/shampoo.py
ml/optimizers/types.py
ml/scripts/__init__.py
ml/scripts/cli.py
ml/scripts/launch.py
ml/scripts/resolve.py
ml/scripts/stage.py
ml/scripts/train.py
ml/tasks/__init__.py
ml/tasks/base.py
ml/tasks/consistency.py
ml/tasks/diffusion.py
ml/tasks/ode.py
ml/tasks/datasets/__init__.py
ml/tasks/datasets/async_iterable.py
ml/tasks/datasets/clippify.py
ml/tasks/datasets/collate.py
ml/tasks/datasets/error_handling.py
ml/tasks/datasets/multi_iter.py
ml/tasks/datasets/samplers.py
ml/tasks/datasets/streaming.py
ml_starter-0.1.91.dist-info/LICENSE
ml_starter-0.1.91.dist-info/METADATA
ml_starter-0.1.91.dist-info/WHEEL
ml_starter-0.1.91.dist-info/top_level.txt
ml_starter-0.1.91.dist-info/RECORD
