Metadata-Version: 2.1
Name: ml-starter
Version: 0.1.91
Summary: ML project template repository
Home-page: https://github.com/codekansas/ml-starter
Author: Benjamin Bolte
Classifier: Development Status :: 4 - Beta
Classifier: Intended Audience :: Developers
Classifier: Topic :: Scientific/Engineering :: Artificial Intelligence
Classifier: License :: OSI Approved :: MIT License
Classifier: Programming Language :: Python :: 3
Requires-Python: >=3.10
License-File: LICENSE
Requires-Dist: av
Requires-Dist: numpy
Requires-Dist: omegaconf
Requires-Dist: psutil
Requires-Dist: sarfile
Requires-Dist: six
Requires-Dist: smart-open
Requires-Dist: soundfile
Requires-Dist: tensorboard
Requires-Dist: torch
Requires-Dist: torchaudio
Requires-Dist: torchvision
Provides-Extra: dev
Requires-Dist: black ; extra == 'dev'
Requires-Dist: darglint ; extra == 'dev'
Requires-Dist: mypy ; extra == 'dev'
Requires-Dist: pytest ; extra == 'dev'
Requires-Dist: pytest-timeout ; extra == 'dev'
Requires-Dist: ruff ; extra == 'dev'
Provides-Extra: docs
Requires-Dist: myst-parser ; extra == 'docs'
Requires-Dist: sphinx ==6.2.1 ; extra == 'docs'
Requires-Dist: sphinxcontrib-jquery ; extra == 'docs'
Requires-Dist: sphinx-rtd-theme ; extra == 'docs'
Requires-Dist: sphinx-autodoc-typehints ; extra == 'docs'
